filer_api/__init__.py
filer_api/admin.py
filer_api/apps.py
filer_api/models.py
filer_api/serializer.py
filer_api/tests.py
filer_api/urls.py
filer_api/views.py
filer_api/migrations/__init__.py
django_filer_api-0.1.dist-info/LICENCE
django_filer_api-0.1.dist-info/METADATA
django_filer_api-0.1.dist-info/WHEEL
django_filer_api-0.1.dist-info/top_level.txt
django_filer_api-0.1.dist-info/RECORD
